biasvariance_toolkit/__init__.py
biasvariance_toolkit/core.py
biasvariance_toolkit-1.0.0.dist-info/licenses/LICENSE
biasvariance_toolkit-1.0.0.dist-info/METADATA
biasvariance_toolkit-1.0.0.dist-info/WHEEL
biasvariance_toolkit-1.0.0.dist-info/top_level.txt
biasvariance_toolkit-1.0.0.dist-info/RECORD
