Metadata-Version: 2.4
Name: biasvariance_toolkit
Version: 1.0.0
Summary: Bias–Variance decomposition toolkit for regression (MSE) and classification (0–1 loss)
Author: Antony Ajay Geoffrey
Author-email: Antony Ajay Geoffrey <ajaygeoffrey456@gmail.com>
License: MIT
Project-URL: Homepage, https://github.com/AntonyAjay123/biasvariance_toolkit
Requires-Python: >=3.8
License-File: LICENSE
Requires-Dist: numpy
Requires-Dist: torch
Requires-Dist: scikit-learn
Requires-Dist: scipy
Dynamic: author
Dynamic: license-file
Dynamic: requires-python
